<?xml version="1.0" encoding="utf-8" ?>
<dwsync>
<file name="gaiguoqiang.jpg" server="10.169.10.112" local="131703534341554483" remote="131703244800000000" Dst="0" />
<file name="hedengcheng.jpg" server="10.169.10.112" local="131703534379168328" remote="131703244800000000" Dst="0" />
<file name="liangfeilong.JPG" server="10.169.10.112" local="131703534331418568" remote="131703244800000000" Dst="0" />
<file name="kemin.jpg" server="10.169.10.112" local="131703534357647496" remote="131703244800000000" Dst="0" />
<file name="lihaixiang.jpg" server="10.169.10.112" local="131703534343824764" remote="131703244800000000" Dst="0" />
<file name="liuqirong.jpg" server="10.169.10.112" local="131703534359973331" remote="131703244800000000" Dst="0" />
<file name="liuweiping.JPG" server="10.169.10.112" local="131624449191413672" remote="131624421600000000" Dst="0" />
<file name="luoli.jpg" server="10.169.10.112" local="131703534362977181" remote="131703244800000000" Dst="0" />
<file name="shisong.jpg" server="10.169.10.112" local="131703534368253164" remote="131703244800000000" Dst="0" />
<file name="wubingxi.jpg" server="10.169.10.112" local="131703534375917107" remote="131703244800000000" Dst="0" />
<file name="yangzhenkun.jpg" server="10.169.10.112" local="131703534381594238" remote="131703244800000000" Dst="0" />
<file name="xiaopeng.jpg" server="10.169.10.112" local="131703534350272992" remote="131703244800000000" Dst="0" />
<file name="yulihua.jpg" server="10.169.10.112" local="131703534383825404" remote="131703244800000000" Dst="0" />
<file name="zhouyanwei.jpg" server="10.169.10.112" local="131703534323681939" remote="131703244800000000" Dst="0" />
<file name="liangfeilong.jpg" server="10.169.10.112" local="131623599942597847" remote="131624998200000000" Dst="0" />
<file name="liuweiping.jpg" server="10.169.10.112" local="131703534365799864" remote="131703244800000000" Dst="0" />
<file name="caisonglu.jpg" server="10.169.10.112" local="131703534338825222" remote="131703244800000000" Dst="0" />
<file name="pengzhiyong.jpg" server="10.169.10.112" local="131703534346740484" remote="131703244800000000" Dst="0" />
<file name="wangyang.jpg" server="10.169.10.112" local="131703534387274006" remote="131703244800000000" Dst="0" />
<file name="Thumbs.db" server="10.169.10.112" local="131703534373271353" remote="131703244800000000" Dst="0" />
</dwsync>